traffic_intersection/__init__.py
traffic_intersection/main.py
traffic_intersection/components/__init__.py
traffic_intersection/components/car.py
traffic_intersection/components/pedestrian.py
traffic_intersection/components/traffic_signals.py
traffic_intersection/components/imglib/cars/blue_car.png
traffic_intersection/components/imglib/cars/blue_car_square.png
traffic_intersection/components/imglib/cars/gray_car.png
traffic_intersection/components/imglib/cars/gray_car_square.png
traffic_intersection/components/imglib/intersection_states/intersection.png
traffic_intersection/components/imglib/intersection_states/intersection_green_green.png
traffic_intersection/components/imglib/intersection_states/intersection_green_red.png
traffic_intersection/components/imglib/intersection_states/intersection_green_yellow.png
traffic_intersection/components/imglib/intersection_states/intersection_red_green.png
traffic_intersection/components/imglib/intersection_states/intersection_red_red.png
traffic_intersection/components/imglib/intersection_states/intersection_red_yellow.png
traffic_intersection/components/imglib/intersection_states/intersection_yellow_green.png
traffic_intersection/components/imglib/intersection_states/intersection_yellow_red.png
traffic_intersection/components/imglib/intersection_states/intersection_yellow_yellow.png
traffic_intersection/components/imglib/pedestrians/walking1.png
traffic_intersection/components/imglib/pedestrians/walking2.png
traffic_intersection/components/imglib/pedestrians/walking3.png
traffic_intersection/contracts/__init__.py
traffic_intersection/contracts/automaton.py
traffic_intersection/contracts/lights_behavior.py
traffic_intersection/contracts/pedestrian_behavior.py
traffic_intersection/contracts/pedestrian_street_combined_behavior.py
traffic_intersection/contracts/planner.py
traffic_intersection/prepare/__init__.py
traffic_intersection/prepare/car_waypoint_graph.py
traffic_intersection-0.1.6.dist-info/METADATA
traffic_intersection-0.1.6.dist-info/RECORD
traffic_intersection-0.1.6.dist-info/WHEEL
traffic_intersection-0.1.6.dist-info/top_level.txt
