Metadata-Version: 2.1
Name: traffic-intersection
Version: 0.1.6
Summary: This is an example of the design-by-contract approach
Home-page: https://github.com/tungminhphan/traffic-intersection
Author: Tung M. Phan
Author-email: tung@caltech.com
License: BSD 3-Clause
Platform: UNKNOWN
Requires-Dist: graphviz
Requires-Dist: imageio
Requires-Dist: scipy
Requires-Dist: numpy
Requires-Dist: matplotlib
Requires-Dist: Pillow
